{
  "version": "1.1.0",
  "runId": "jan-8",
  "org": "oddessentials",
  "startTime": "2026-01-13T21:11:07.383Z",
  "endTime": "2026-01-13T21:11:25.205Z",
  "repos": [
    {
      "project": "engineering",
      "repoName": "backdate-demo-jan-8",
      "repoId": "bfc25b28-c079-4302-a456-d03b452cdec5",
      "resolvedNaming": "isolated",
      "branchesCreated": 3,
      "prs": [
        {
          "prId": 117,
          "title": "[jan-8] chore/jan-8-1",
          "creator": "petepalles@gmail.com",
          "reviewers": [
            {
              "email": "admin@oddessentials.com",
              "vote": "approveWithSuggestions"
            }
          ],
          "comments": 3,
          "followUpCommitsAdded": 0,
          "outcome": "complete",
          "outcomeApplied": true
        },
        {
          "prId": 118,
          "title": "[jan-8] feature/jan-8-0",
          "creator": "petepalles@hotmail.com",
          "reviewers": [
            {
              "email": "petepalles@gmail.com",
              "vote": "approve"
            },
            {
              "email": "admin@oddessentials.com",
              "vote": "approve"
            }
          ],
          "comments": 3,
          "followUpCommitsAdded": 1,
          "outcome": "complete",
          "outcomeApplied": true
        }
      ],
      "failures": []
    }
  ],
  "fatalFailure": null
}